<annotationInfo>
<annotationInfo>
<item  id="1069" filename="vhls/convolution.cpp" linenumber="117" name="exitcond1" contextFuncName="hw_conv" moduleName="hw_conv" rtlName="exitcond1_fu_5290_p2" latency="0" BRAM="-1" DSP="-1" FF="0" LUT="18" fileDirectory="D:\Jacob\Documents\ECE_1195\Lab_5"><\/item>
<item  id="1071" filename="vhls/convolution.cpp" linenumber="117" name="i_1" contextFuncName="hw_conv" moduleName="hw_conv" rtlName="i_1_fu_5296_p2" latency="0" BRAM="-1" DSP="-1" FF="0" LUT="26" fileDirectory="D:\Jacob\Documents\ECE_1195\Lab_5"><\/item>
<item  id="1590" filename="vhls/convolution.cpp" linenumber="149" name="kbuf_0_1" contextFuncName="hw_conv" moduleName="hw_conv" rtlName="hw_conv_mux_5099_bkb_U1" latency="0" BRAM="-1" DSP="-1" FF="-1" LUT="-1" fileDirectory="D:\Jacob\Documents\ECE_1195\Lab_5"><\/item>
<item  id="3630" filename="vhls/convolution.cpp" linenumber="163" name="kbuf_1_2" contextFuncName="hw_conv" moduleName="hw_conv" rtlName="hw_conv_mux_5099_bkb_U2" latency="0" BRAM="-1" DSP="-1" FF="-1" LUT="-1" fileDirectory="D:\Jacob\Documents\ECE_1195\Lab_5"><\/item>
<item  id="5161" filename="vhls/convolution.cpp" linenumber="174" name="tmp_4" contextFuncName="hw_conv" moduleName="hw_conv" rtlName="tmp_4_fu_5302_p3" latency="0" BRAM="-1" DSP="-1" FF="-1" LUT="-1" fileDirectory="D:\Jacob\Documents\ECE_1195\Lab_5"><\/item>
<item  id="5170" filename="vhls/convolution.cpp" linenumber="182" name="loc_1" contextFuncName="hw_conv" moduleName="hw_conv" rtlName="loc_1_fu_5319_p2" latency="0" BRAM="-1" DSP="-1" FF="0" LUT="15" fileDirectory="D:\Jacob\Documents\ECE_1195\Lab_5"><\/item>
<item  id="5171" filename="vhls/convolution.cpp" linenumber="183" name="tmp_1" contextFuncName="hw_conv" moduleName="hw_conv" rtlName="tmp_1_fu_5325_p2" latency="0" BRAM="-1" DSP="-1" FF="0" LUT="13" fileDirectory="D:\Jacob\Documents\ECE_1195\Lab_5"><\/item>
<item  id="5172" filename="vhls/convolution.cpp" linenumber="183" name="tmp_2" contextFuncName="hw_conv" moduleName="hw_conv" rtlName="tmp_2_fu_5331_p2" latency="0" BRAM="-1" DSP="-1" FF="0" LUT="15" fileDirectory="D:\Jacob\Documents\ECE_1195\Lab_5"><\/item>
<item  id="5173" filename="vhls/convolution.cpp" linenumber="183" name="loc_2" contextFuncName="hw_conv" moduleName="hw_conv" rtlName="loc_2_fu_5337_p3" latency="0" BRAM="-1" DSP="-1" FF="0" LUT="9" fileDirectory="D:\Jacob\Documents\ECE_1195\Lab_5"><\/item>
<item  id="5174" filename="vhls/convolution.cpp" linenumber="211" name="tmp_cast" contextFuncName="hw_conv" moduleName="hw_conv" rtlName="tmp_cast_fu_15602_p1" latency="0" BRAM="-1" DSP="-1" FF="-1" LUT="-1" fileDirectory="D:\Jacob\Documents\ECE_1195\Lab_5"><\/item>
<item  id="5175" filename="vhls/convolution.cpp" linenumber="211" name="tmp_18_1" contextFuncName="hw_conv" moduleName="hw_conv" rtlName="tmp_18_1_fu_15606_p3" latency="0" BRAM="-1" DSP="-1" FF="-1" LUT="-1" fileDirectory="D:\Jacob\Documents\ECE_1195\Lab_5"><\/item>
<item  id="5176" filename="vhls/convolution.cpp" linenumber="211" name="tmp_18_1_cast" contextFuncName="hw_conv" moduleName="hw_conv" rtlName="tmp_18_1_cast_fu_15614_p1" latency="0" BRAM="-1" DSP="-1" FF="-1" LUT="-1" fileDirectory="D:\Jacob\Documents\ECE_1195\Lab_5"><\/item>
<item  id="5177" filename="vhls/convolution.cpp" linenumber="211" name="tmp_15_2_cast" contextFuncName="hw_conv" moduleName="hw_conv" rtlName="tmp_15_2_cast_fu_15618_p1" latency="0" BRAM="-1" DSP="-1" FF="-1" LUT="-1" fileDirectory="D:\Jacob\Documents\ECE_1195\Lab_5"><\/item>
<item  id="5178" filename="vhls/convolution.cpp" linenumber="211" name="tmp_18_3" contextFuncName="hw_conv" moduleName="hw_conv" rtlName="tmp_18_3_fu_15622_p3" latency="0" BRAM="-1" DSP="-1" FF="-1" LUT="-1" fileDirectory="D:\Jacob\Documents\ECE_1195\Lab_5"><\/item>
<item  id="5179" filename="vhls/convolution.cpp" linenumber="211" name="tmp_18_3_cast" contextFuncName="hw_conv" moduleName="hw_conv" rtlName="tmp_18_3_cast_fu_15630_p1" latency="0" BRAM="-1" DSP="-1" FF="-1" LUT="-1" fileDirectory="D:\Jacob\Documents\ECE_1195\Lab_5"><\/item>
<item  id="5180" filename="vhls/convolution.cpp" linenumber="211" name="tmp_18_4" contextFuncName="hw_conv" moduleName="hw_conv" rtlName="tmp_18_4_fu_15634_p3" latency="0" BRAM="-1" DSP="-1" FF="-1" LUT="-1" fileDirectory="D:\Jacob\Documents\ECE_1195\Lab_5"><\/item>
<item  id="5181" filename="vhls/convolution.cpp" linenumber="211" name="tmp_18_4_cast" contextFuncName="hw_conv" moduleName="hw_conv" rtlName="tmp_18_4_cast_fu_15642_p1" latency="0" BRAM="-1" DSP="-1" FF="-1" LUT="-1" fileDirectory="D:\Jacob\Documents\ECE_1195\Lab_5"><\/item>
<item  id="5182" filename="vhls/convolution.cpp" linenumber="211" name="tmp_18_5" contextFuncName="hw_conv" moduleName="hw_conv" rtlName="tmp_18_5_fu_15646_p3" latency="0" BRAM="-1" DSP="-1" FF="-1" LUT="-1" fileDirectory="D:\Jacob\Documents\ECE_1195\Lab_5"><\/item>
<item  id="5183" filename="vhls/convolution.cpp" linenumber="211" name="tmp_18_5_cast" contextFuncName="hw_conv" moduleName="hw_conv" rtlName="tmp_18_5_cast_fu_15654_p1" latency="0" BRAM="-1" DSP="-1" FF="-1" LUT="-1" fileDirectory="D:\Jacob\Documents\ECE_1195\Lab_5"><\/item>
<item  id="5184" filename="vhls/convolution.cpp" linenumber="211" name="tmp_15_6_cast" contextFuncName="hw_conv" moduleName="hw_conv" rtlName="tmp_15_6_cast_fu_15658_p1" latency="0" BRAM="-1" DSP="-1" FF="-1" LUT="-1" fileDirectory="D:\Jacob\Documents\ECE_1195\Lab_5"><\/item>
<item  id="5185" filename="vhls/convolution.cpp" linenumber="211" name="tmp_18_7" contextFuncName="hw_conv" moduleName="hw_conv" rtlName="tmp_18_7_fu_15662_p3" latency="0" BRAM="-1" DSP="-1" FF="-1" LUT="-1" fileDirectory="D:\Jacob\Documents\ECE_1195\Lab_5"><\/item>
<item  id="5186" filename="vhls/convolution.cpp" linenumber="211" name="tmp_18_7_cast" contextFuncName="hw_conv" moduleName="hw_conv" rtlName="tmp_18_7_cast_fu_15669_p1" latency="0" BRAM="-1" DSP="-1" FF="-1" LUT="-1" fileDirectory="D:\Jacob\Documents\ECE_1195\Lab_5"><\/item>
<item  id="5187" filename="vhls/convolution.cpp" linenumber="211" name="tmp_15_8_cast" contextFuncName="hw_conv" moduleName="hw_conv" rtlName="tmp_15_8_cast_fu_15673_p1" latency="0" BRAM="-1" DSP="-1" FF="-1" LUT="-1" fileDirectory="D:\Jacob\Documents\ECE_1195\Lab_5"><\/item>
<item  id="5188" filename="vhls/convolution.cpp" linenumber="211" name="tmp5" contextFuncName="hw_conv" moduleName="hw_conv" rtlName="tmp5_fu_15677_p2" latency="0" BRAM="-1" DSP="-1" FF="0" LUT="13" fileDirectory="D:\Jacob\Documents\ECE_1195\Lab_5"><\/item>
<item  id="5189" filename="vhls/convolution.cpp" linenumber="211" name="tmp1020_cast" contextFuncName="hw_conv" moduleName="hw_conv" rtlName="tmp1020_cast_fu_15711_p1" latency="0" BRAM="-1" DSP="-1" FF="-1" LUT="-1" fileDirectory="D:\Jacob\Documents\ECE_1195\Lab_5"><\/item>
<item  id="5190" filename="vhls/convolution.cpp" linenumber="211" name="tmp6" contextFuncName="hw_conv" moduleName="hw_conv" rtlName="tmp6_fu_15683_p2" latency="0" BRAM="-1" DSP="-1" FF="0" LUT="14" fileDirectory="D:\Jacob\Documents\ECE_1195\Lab_5"><\/item>
<item  id="5191" filename="vhls/convolution.cpp" linenumber="211" name="tmp1021_cast" contextFuncName="hw_conv" moduleName="hw_conv" rtlName="tmp1021_cast_fu_15714_p1" latency="0" BRAM="-1" DSP="-1" FF="-1" LUT="-1" fileDirectory="D:\Jacob\Documents\ECE_1195\Lab_5"><\/item>
<item  id="5192" filename="vhls/convolution.cpp" linenumber="211" name="tmp7" contextFuncName="hw_conv" moduleName="hw_conv" rtlName="tmp7_fu_15717_p2" latency="0" BRAM="-1" DSP="-1" FF="0" LUT="12" fileDirectory="D:\Jacob\Documents\ECE_1195\Lab_5"><\/item>
<item  id="5193" filename="vhls/convolution.cpp" linenumber="211" name="tmp8" contextFuncName="hw_conv" moduleName="hw_conv" rtlName="tmp8_fu_15689_p2" latency="0" BRAM="-1" DSP="-1" FF="0" LUT="14" fileDirectory="D:\Jacob\Documents\ECE_1195\Lab_5"><\/item>
<item  id="5194" filename="vhls/convolution.cpp" linenumber="211" name="tmp1023_cast" contextFuncName="hw_conv" moduleName="hw_conv" rtlName="tmp1023_cast_fu_15723_p1" latency="0" BRAM="-1" DSP="-1" FF="-1" LUT="-1" fileDirectory="D:\Jacob\Documents\ECE_1195\Lab_5"><\/item>
<item  id="5195" filename="vhls/convolution.cpp" linenumber="211" name="tmp9" contextFuncName="hw_conv" moduleName="hw_conv" rtlName="tmp9_fu_15695_p2" latency="0" BRAM="-1" DSP="-1" FF="0" LUT="15" fileDirectory="D:\Jacob\Documents\ECE_1195\Lab_5"><\/item>
<item  id="5196" filename="vhls/convolution.cpp" linenumber="211" name="tmp1025_cast" contextFuncName="hw_conv" moduleName="hw_conv" rtlName="tmp1025_cast_fu_15701_p1" latency="0" BRAM="-1" DSP="-1" FF="-1" LUT="-1" fileDirectory="D:\Jacob\Documents\ECE_1195\Lab_5"><\/item>
<item  id="5197" filename="vhls/convolution.cpp" linenumber="211" name="tmp3" contextFuncName="hw_conv" moduleName="hw_conv" rtlName="tmp3_fu_15705_p2" latency="0" BRAM="-1" DSP="-1" FF="0" LUT="14" fileDirectory="D:\Jacob\Documents\ECE_1195\Lab_5"><\/item>
<item  id="5198" filename="vhls/convolution.cpp" linenumber="211" name="tmp1024_cast" contextFuncName="hw_conv" moduleName="hw_conv" rtlName="tmp1024_cast_fu_15726_p1" latency="0" BRAM="-1" DSP="-1" FF="-1" LUT="-1" fileDirectory="D:\Jacob\Documents\ECE_1195\Lab_5"><\/item>
<item  id="5199" filename="vhls/convolution.cpp" linenumber="211" name="tmp4" contextFuncName="hw_conv" moduleName="hw_conv" rtlName="tmp4_fu_15729_p2" latency="0" BRAM="-1" DSP="-1" FF="0" LUT="13" fileDirectory="D:\Jacob\Documents\ECE_1195\Lab_5"><\/item>
<item  id="5200" filename="vhls/convolution.cpp" linenumber="211" name="tmp1022_cast" contextFuncName="hw_conv" moduleName="hw_conv" rtlName="tmp1022_cast_fu_15735_p1" latency="0" BRAM="-1" DSP="-1" FF="-1" LUT="-1" fileDirectory="D:\Jacob\Documents\ECE_1195\Lab_5"><\/item>
<item  id="5201" filename="vhls/convolution.cpp" linenumber="211" name="result_2_8" contextFuncName="hw_conv" moduleName="hw_conv" rtlName="result_2_8_fu_15739_p2" latency="0" BRAM="-1" DSP="-1" FF="0" LUT="12" fileDirectory="D:\Jacob\Documents\ECE_1195\Lab_5"><\/item>
<item  id="5202" filename="vhls/convolution.cpp" linenumber="211" name="tmp_V" contextFuncName="hw_conv" moduleName="hw_conv" rtlName="sout_V_data_V_1_payload_B" latency="0" BRAM="-1" DSP="-1" FF="-1" LUT="-1" fileDirectory="D:\Jacob\Documents\ECE_1195\Lab_5"><\/item>
<item  id="5203" filename="vhls/convolution.cpp" linenumber="231" name="tmp_3" contextFuncName="hw_conv" moduleName="hw_conv" rtlName="tmp_3_fu_5345_p2" latency="0" BRAM="-1" DSP="-1" FF="0" LUT="18" fileDirectory="D:\Jacob\Documents\ECE_1195\Lab_5"><\/item>
<item  id="5206" filename="vhls/convolution.cpp" linenumber="235" name="tmp_last_V" contextFuncName="hw_conv" moduleName="hw_conv" rtlName="tmp_last_V_fu_5351_p2" latency="0" BRAM="-1" DSP="-1" FF="0" LUT="18" fileDirectory="D:\Jacob\Documents\ECE_1195\Lab_5"><\/item>
<\/annotationInfo>
</annotationInfo>
